mnist/__init__.py
mnist/__main__.py
mnist/__version__.py
mnist/config.py
mnist/config_test.py
mnist/dataset.py
mnist/dataset_test.py
mnist/files.py
mnist/files_test.py
mnist/model.py
mnist/model_test.py
mnist/preprocess.py
mnist/train.py
mnist_pipeline-0.2.2.dist-info/LICENSE
mnist_pipeline-0.2.2.dist-info/METADATA
mnist_pipeline-0.2.2.dist-info/WHEEL
mnist_pipeline-0.2.2.dist-info/entry_points.txt
mnist_pipeline-0.2.2.dist-info/top_level.txt
mnist_pipeline-0.2.2.dist-info/RECORD
